{"game": {"id": 42080, "teseraId": 2038285, "bggId": 0, "title": "\u0410\u0440\u0445\u0438\u0442\u0435\u043a\u0442\u043e\u0440\u044b \u0437\u0430\u043f\u0430\u0434\u043d\u043e\u0433\u043e \u043a\u043e\u0440\u043e\u043b\u0435\u0432\u0441\u0442\u0432\u0430: \u043a\u043e\u043b\u043b\u0435\u043a\u0446\u0438\u043e\u043d\u043d\u0430\u044f \u043a\u043e\u0440\u043e\u0431\u043a\u0430", "title2": "Architects of the West Kingdom: Collector's Box", "alias": "architects-of-the-west-kingdom-collectors-box", "descriptionShort": "", "description": "<p><strong><i>Collector's Box </i></strong>&mdash; \u0441\u0438\u0441\u0442\u0435\u043c\u0430 \u0445\u0440\u0430\u043d\u043d\u0435\u043d\u0438\u044f \u0438\u0433\u0440\u044b <i>Architects of the West Kingdom</i> \u0438 \u0435\u0435 \u0434\u043e\u043f\u043e\u043b\u043d\u0435\u043d\u0438\u0435\u0439 <i>Works of Wonder</i>, <i>Age of Artisans</i>, \u0430 \u0442\u0430\u043a\u0436\u0435 \u0432\u0441\u0435\u0433\u043e \u0434\u043e\u043f\u043e\u043b\u043d\u0438\u0442\u0435\u043b\u044c\u043d\u043e\u0433\u043e \u043a\u043e\u043d\u0442\u0435\u043d\u0442\u0430, \u043d\u0430\u043f\u0440\u0438\u043c\u0435\u0440, \u043f\u0440\u043e\u043c\u043e \u0438 \u043c\u0435\u0442\u0430\u043b\u043b\u0438\u0447\u0435\u0441\u043a\u0438\u0445 \u043c\u043e\u043d\u0435\u0442.</p>\r\n<p><strong><i>&nbsp;</i></strong></p>\r\n<p>\u041a\u0440\u043e\u043c\u0435 \u043a\u043e\u0440\u043e\u0431\u043a\u0438 \u0438 \u043e\u0440\u0433\u0430\u043d\u0430\u0439\u0437\u0435\u0440\u0430 \u0441\u043e\u0434\u0435\u0440\u0436\u0438\u0442 \u043d\u0430\u0431\u043e\u0440 \u043f\u0440\u043e\u043c\u043e-\u043a\u0430\u0440\u0442 (4 \u043a\u0430\u0440\u0442\u044b \u0443\u043a\u0440\u0430\u0448\u0435\u043d\u0438\u0439, 3 \u043a\u0430\u0440\u0442\u044b \u0437\u0434\u0430\u043d\u0438\u0439, 6 \u043a\u0430\u0440\u0442 \u0443\u0447\u0435\u043d\u0438\u043a\u043e\u0432, 1 \u043a\u0430\u0440\u0442\u0430 \u0432\u043b\u0438\u044f\u043d\u0438\u044f).</p>\r\n<p>&nbsp;</p>\r\n<p>\u041d\u0435 \u0441\u043e\u0434\u0435\u0440\u0436\u0438\u0442 \u0431\u0430\u0437\u043e\u0432\u0443\u044e \u0438\u0433\u0440\u0443 \u0438 \u0435\u0435 \u0434\u043e\u043f\u043e\u043b\u043d\u0435\u043d\u0438\u044f!</p>", "modificationDateUtc": "2023-02-24T18:14:16", "creationDateUtc": "2022-02-18T23:05:57", "photoUrl": "https://s.tesera.ru/images/items/2038285,3/photo1.jpg", "year": 2022, "ratingUser": 6.75, "n10Rating": 0.0, "n20Rating": 0.0, "bggRating": 0.0, "bggGeekRating": 0.0, "bggNumVotes": 0, "numVotes": 2, "playersMin": 1, "playersMax": 6, "playersMinRecommend": 0, "playersMaxRecommend": 0, "playersAgeMin": 12, "timeToLearn": 0, "playtimeMin": 60, "playtimeMax": 80, "commentsTotal": 1, "commentsTotalNew": 0, "teseraUrl": "https://tesera.ru/game/2038285", "isAddition": true}, "ownersTotal": 51, "sellTotal": 1, "buyTotal": 0, "sellTotalAll": 0, "buyTotalAll": 0, "commentsTotal": 1, "reportsTotal": 0, "photosTotal": 1, "filesTotal": 0, "linksTotal": 0, "videoExternalTotal": 0, "videoInternalTotal": 0, "photos": [{"teseraId": 2136345, "title": "\u043f\u0440\u043e\u043c\u043a\u0438", "photoUrl": "https://s.tesera.ru/images/items/2136345/1600x1200xsxy/photo.jpg", "creationDateUtc": "2022-09-21T16:41:40", "commentsTotal": 0, "author": {"teseraId": 1358528, "id": 37962, "login": "tigra1", "name": "tigra", "avatarUrl": "https://s.tesera.ru/images/items/1358528,22/photo.jpg", "rating": 20719, "teseraUrl": "https://tesera.ru/user/1358528"}}], "files": [], "links": [], "similars": [], "relateds": [], "news": []}