{"game": {"id": 38534, "teseraId": 1793247, "bggId": 0, "title": "Keyflower: Delivery Man", "alias": "keyflower-delivery-man", "descriptionShort": "", "description": "<p>Starting on the delivery man tile, travel as far as possible along the road without travelling along the same length of road twice.</p>\r\n<p>&nbsp;</p>\r\n<p>Crossing over a length of road previously travelled along is permitted. Score one point for each different tile on which you have travelled</p>", "modificationDateUtc": "2021-02-12T13:40:49", "creationDateUtc": "2020-12-17T21:48:48", "photoUrl": "https://s.tesera.ru/images/items/1793247,3/photo1.jpg", "photoUrl2": "https://s.tesera.ru/images/items/1793247,3/photo2.jpg", "year": 2018, "ratingUser": 0.0, "n10Rating": 0.0, "n20Rating": 0.0, "bggRating": 0.0, "bggGeekRating": 0.0, "bggNumVotes": 0, "numVotes": 0, "playersMin": 0, "playersMax": 0, "playersMinRecommend": 0, "playersMaxRecommend": 0, "playersAgeMin": 0, "timeToLearn": 0, "playtimeMin": 0, "playtimeMax": 0, "commentsTotal": 0, "commentsTotalNew": 0, "teseraUrl": "https://tesera.ru/game/1793247", "isAddition": true}, "ownersTotal": 4, "sellTotal": 0, "buyTotal": 2, "sellTotalAll": 0, "buyTotalAll": 0, "commentsTotal": 0, "reportsTotal": 0, "photosTotal": 0, "filesTotal": 0, "linksTotal": 0, "videoExternalTotal": 0, "videoInternalTotal": 0, "photos": [], "files": [], "links": [], "similars": [], "relateds": [{"id": 6066, "teseraId": 300638, "bggId": 144058, "title": "Keyflower: The Farmers", "alias": "Keyflower-The-Farmers", "descriptionShort": "", "creationDateUtc": "2013-08-13T20:03:10", "photoUrl": "https://s.tesera.ru/images/items/300638,3/200x200xpa/photo1.jpg", "year": 2013, "numVotes": 22, "ratingUser": 8.23, "n10Rating": 7.27, "n20Rating": 6.77, "bggRating": 7.849, "bggGeekRating": 6.413, "bggNumVotes": 1219, "commentsTotal": 9, "commentsTotalNew": 0, "isAddition": true}, {"id": 6146, "teseraId": 306807, "bggId": 141816, "title": "Keyflower: Emporium & Monument", "alias": "keyflower-emporium-monument", "descriptionShort": "", "creationDateUtc": "2013-08-28T14:12:26", "photoUrl": "https://s.tesera.ru/images/items/306807,3/200x200xpa/photo1.jpg", "year": 2013, "numVotes": 5, "ratingUser": 6.7, "n10Rating": 0.0, "n20Rating": 0.0, "bggRating": 7.552, "bggGeekRating": 5.778, "bggNumVotes": 299, "commentsTotal": 3, "commentsTotalNew": 0, "isAddition": true}, {"id": 6167, "teseraId": 308897, "bggId": 140936, "title": "Keyflower: Key Celeste", "alias": "keyflower-key-celeste", "descriptionShort": "Keyflower: Key Celeste - \u043f\u0440\u043e\u043c\u043e \u0434\u043e\u043f\u043e\u043b\u043d\u0435\u043d\u0438\u0435, \u0441\u043e\u0441\u0442\u043e\u044f\u0449\u0435\u0435 \u0438\u0437 \u043e\u0434\u043d\u043e\u0433\u043e \u0442\u0430\u0439\u043b\u0430 \u043a\u043e\u0440\u0430\u0431\u043b\u044f \u0438 \u0434\u0435\u0440\u0435\u0432\u044f\u043d\u043d\u043e\u0439 \u0444\u0438\u0433\u0443\u0440\u043a\u0438 \u043f\u0440\u0438\u0432\u0438\u0434\u0435\u043d\u0438\u044f.", "creationDateUtc": "2013-09-02T20:25:10", "photoUrl": "https://s.tesera.ru/images/items/308897,3/200x200xpa/photo1.jpg", "year": 2013, "numVotes": 5, "ratingUser": 7.2, "n10Rating": 0.0, "n20Rating": 0.0, "bggRating": 7.418, "bggGeekRating": 5.837, "bggNumVotes": 412, "commentsTotal": 3, "commentsTotalNew": 0, "isAddition": true}, {"id": 7494, "teseraId": 432835, "bggId": 163572, "title": "Keyflower: The Merchants", "alias": "keyflower-the-merchants", "descriptionShort": "", "creationDateUtc": "2014-08-08T13:38:24", "photoUrl": "https://s.tesera.ru/images/items/432835,3/200x200xpa/photo1.jpg", "year": 2014, "numVotes": 12, "ratingUser": 7.62, "n10Rating": 6.51, "n20Rating": 0.0, "bggRating": 8.104, "bggGeekRating": 6.369, "bggNumVotes": 945, "commentsTotal": 14, "commentsTotalNew": 0, "isAddition": true}, {"id": 8110, "teseraId": 490263, "bggId": 147380, "title": "Keyflower: Storyteller", "alias": "Keyflower-Storyteller", "descriptionShort": "", "creationDateUtc": "2015-01-05T11:47:32", "photoUrl": "https://s.tesera.ru/images/items/490263,3/200x200xpa/photo1.png", "year": 2013, "numVotes": 4, "ratingUser": 7.06, "n10Rating": 0.0, "n20Rating": 0.0, "bggRating": 7.64, "bggGeekRating": 5.715, "bggNumVotes": 213, "commentsTotal": 0, "commentsTotalNew": 0, "isAddition": true}, {"id": 8111, "teseraId": 490268, "bggId": 163742, "title": "Keyflower: Trader", "alias": "Keyflower-Trader", "descriptionShort": "", "creationDateUtc": "2015-01-05T11:55:07", "photoUrl": "https://s.tesera.ru/images/items/490268,3/200x200xpa/photo1.png", "year": 2014, "numVotes": 3, "ratingUser": 6.42, "n10Rating": 0.0, "n20Rating": 0.0, "bggRating": 7.605, "bggGeekRating": 5.69, "bggNumVotes": 189, "commentsTotal": 0, "commentsTotalNew": 0, "isAddition": true}, {"id": 8112, "teseraId": 490270, "bggId": 162647, "title": "Keyflower: Beekeeper", "alias": "Keyflower-Beekeeper", "descriptionShort": "", "creationDateUtc": "2015-01-05T11:59:20", "photoUrl": "https://s.tesera.ru/images/items/490270,3/200x200xpa/photo1.png", "year": 2014, "numVotes": 3, "ratingUser": 7.59, "n10Rating": 0.0, "n20Rating": 0.0, "bggRating": 7.565, "bggGeekRating": 5.712, "bggNumVotes": 218, "commentsTotal": 3, "commentsTotalNew": 0, "isAddition": true}, {"id": 12167, "teseraId": 871673, "bggId": 205504, "title": "Keyflower: Keymelequin", "alias": "keyflower-keymelequin", "descriptionShort": "", "creationDateUtc": "2016-11-04T20:50:08", "photoUrl": "https://s.tesera.ru/images/items/871673,3/200x200xpa/photo1.jpg", "year": 2016, "numVotes": 0, "ratingUser": 0.0, "n10Rating": 0.0, "n20Rating": 0.0, "bggRating": 7.713, "bggGeekRating": 5.68, "bggNumVotes": 168, "commentsTotal": 0, "commentsTotalNew": 0, "isAddition": true}, {"id": 29418, "teseraId": 1253015, "bggId": 245169, "title": "Keyflower: Boat 7", "alias": "keyflower-Boat7", "descriptionShort": "", "creationDateUtc": "2018-05-12T08:09:17", "photoUrl": "https://s.tesera.ru/images/items/1253015,3/200x200xpa/photo1.jpg", "year": 2018, "numVotes": 0, "ratingUser": 0.0, "n10Rating": 0.0, "n20Rating": 0.0, "bggRating": 7.723, "bggGeekRating": 5.594, "bggNumVotes": 85, "commentsTotal": 0, "commentsTotalNew": 0, "isAddition": true}, {"id": 29419, "teseraId": 1253028, "bggId": 245170, "title": "Keyflower: Sorcerer", "alias": "keyflower-sorcerer", "descriptionShort": "", "creationDateUtc": "2018-05-12T08:31:48", "photoUrl": "https://s.tesera.ru/images/items/1253028,3/200x200xpa/photo1.jpg", "year": 2018, "numVotes": 0, "ratingUser": 0.0, "n10Rating": 0.0, "n20Rating": 0.0, "bggRating": 7.794, "bggGeekRating": 5.604, "bggNumVotes": 92, "commentsTotal": 0, "commentsTotalNew": 0, "isAddition": true}, {"id": 33779, "teseraId": 1414487, "bggId": 0, "title": "Keyflower: Developer", "alias": "keyflower-developer", "descriptionShort": "", "creationDateUtc": "2019-02-28T21:18:24", "photoUrl": "https://s.tesera.ru/images/items/1414487,3/200x200xpa/photo1.jpg", "year": 2018, "numVotes": 1, "ratingUser": 5.0, "n10Rating": 0.0, "n20Rating": 0.0, "bggRating": 0.0, "bggGeekRating": 0.0, "bggNumVotes": 0, "commentsTotal": 0, "commentsTotalNew": 0, "isAddition": true}], "news": []}