{"game": {"id": 44405, "teseraId": 2166139, "bggId": 0, "title": "\u041a\u043e\u043c\u043f\u043b\u0435\u043a\u0442 \u043f\u0440\u043e\u043c\u043e\u043a\u0430\u0440\u0442 \u0434\u043b\u044f \u0438\u0433\u0440\u044b \u00ab\u0421\u0435\u0440\u043f\u00bb \u21161", "alias": "komplekt-promokart-dlya-igry-serp-1", "descriptionShort": "", "modificationDateUtc": "2022-12-10T07:27:02", "creationDateUtc": "2022-12-10T07:26:24", "photoUrl": "https://s.tesera.ru/images/items/2166139,3/photo1.png", "year": 0, "ratingUser": 0.0, "n10Rating": 0.0, "n20Rating": 0.0, "bggRating": 0.0, "bggGeekRating": 0.0, "bggNumVotes": 0, "numVotes": 0, "playersMin": 0, "playersMax": 0, "playersMinRecommend": 0, "playersMaxRecommend": 0, "playersAgeMin": 0, "timeToLearn": 0, "playtimeMin": 0, "playtimeMax": 0, "commentsTotal": 0, "commentsTotalNew": 0, "teseraUrl": "https://tesera.ru/game/2166139", "isAddition": false}, "ownersTotal": 0, "sellTotal": 0, "buyTotal": 0, "sellTotalAll": 0, "buyTotalAll": 0, "commentsTotal": 0, "reportsTotal": 0, "photosTotal": 0, "filesTotal": 0, "linksTotal": 0, "videoExternalTotal": 0, "videoInternalTotal": 0, "photos": [], "files": [], "links": [], "similars": [], "relateds": [], "news": []}