{"game": {"id": 4027, "teseraId": 115777, "bggId": 103091, "title": "Settlers of Catan: Dawn of the Merchants", "title3": "Die Siedler von Catan - Aufbruch der H\u00e4ndler, \u041a\u043e\u043b\u043e\u043d\u0438\u0437\u0430\u0442\u043e\u0440\u044b. \u0415\u0432\u0440\u043e\u043f\u0430", "alias": "settlers-of-catan-dawn-of-the-merchants", "descriptionShort": "", "description": "<p>&nbsp;</p>\r\n<div id=\"gt-res-wrap\">\r\n<div id=\"gt-res-content\" class=\"almost_half_cell\">\r\n<div style=\"text-align: justify;\" dir=\"ltr\"><span id=\"result_box\" lang=\"ru\"><span class=\"hps\">\u0418\u0433\u0440\u043e\u043a\u0438 \u043d\u0430\u0447\u0438\u043d\u0430\u044e\u0442</span>&nbsp;\u0432&nbsp;<span class=\"hps\">\u0442\u0440\u0435\u0445 \u043c\u0435\u0441\u0442\u0430\u0445&nbsp;</span><span class=\"hps\">\u043d\u0430 \u0438\u0433\u0440\u043e\u0432\u043e\u043c \u043f\u043e\u043b\u0435</span>, \u0441\u043e\u0431\u0438\u0440\u0430\u044e\u0442&nbsp;<span class=\"hps\">\u0440\u0435\u0441\u0443\u0440\u0441\u044b</span>&nbsp;<span class=\"hps\">\u0432 \u0437\u0430\u0432\u0438\u0441\u0438\u043c\u043e\u0441\u0442\u0438 \u043e\u0442</span>&nbsp;<span class=\"hps\">\u0431\u0440\u043e\u0441\u043a\u0430 \u043a\u0443\u0431\u0438\u043a\u043e\u0432</span>, \u0440\u0430\u0441\u0445\u043e\u0434\u0443\u044e\u0442 \u0438\u0445&nbsp;<span class=\"hps\">\u043d\u0430&nbsp;</span><span class=\"hps\">\u043f\u0435\u0440\u0435\u043c\u0435\u0449\u0435\u043d\u0438\u0435 \u0438</span>&nbsp;<span class=\"hps\">\u0441\u0442\u0440\u043e\u0438\u0442\u0435\u043b\u044c\u0441\u0442\u0432\u043e.&nbsp;<span>\u041f\u043e\u0431\u0435\u0436\u0434\u0430\u0435\u0442 \u0438\u0433\u0440\u043e\u043a, \u043a\u043e\u0442\u043e\u0440\u044b\u0439 \u0440\u0430\u043d\u044c\u0448\u0435 \u0434\u0440\u0443\u0433\u0438\u0445 \u0440\u0430\u0437\u0432\u0435\u0437\u0435\u0442 \u0432\u0441\u0435 \u0442\u043e\u0432\u0430\u0440\u044b \u0441\u043e \u0441\u0432\u043e\u0435\u0433\u043e \u0441\u043a\u043b\u0430\u0434\u0430 \u043f\u043e \"\u0442\u043e\u0440\u0433\u043e\u0432\u044b\u043c \u0440\u044f\u0434\u0430\u043c\" \u0440\u0430\u0437\u043d\u044b\u0445 \u0433\u043e\u0440\u043e\u0434\u043e\u0432.&nbsp;</span></span></span></div>\r\n<div style=\"text-align: justify;\" dir=\"ltr\"><span id=\"result_box\" lang=\"ru\"><br /><span class=\"hps\">\u0412 \u043e\u0442\u043b\u0438\u0447\u0438\u0435 \u043e\u0442 <i>Settlers of America: Trails to Rails, </i>\u0433\u0434\u0435 \u0438\u0433\u0440\u0430 \u043f\u0440\u043e\u0445\u043e\u0434\u0438\u0442 \u043d\u0430 \u043a\u0430\u0442\u0430\u043d\u043e\u043f\u043e\u0434\u043e\u0431\u043d\u043e\u0439 \u043a\u0430\u0440\u0442\u0435&nbsp;</span><span class=\"hps\">\u0421\u043e\u0435\u0434\u0438\u043d\u0435\u043d\u043d\u044b\u0445 \u0428\u0442\u0430\u0442\u043e\u0432</span><span>, \u0432 \"<i>\u0420\u0430\u0441\u0446\u0432\u0435\u0442\u0435 \u0422\u043e\u0440\u0433\u043e\u0432\u043b\u0438</i>\" \u0438\u0441\u043f\u043e\u043b\u044c\u0437\u0443\u0435\u0442\u0441\u044f \u043a\u0430\u0442\u0430\u043d\u043e\u043f\u043e\u0434\u043e\u0431\u043d\u0430\u044f \u043a\u0430\u0440\u0442\u0430&nbsp;</span><span class=\"hps\">\u0415\u0432\u0440\u043e\u043f\u044b. \u042d\u0442\u043e \u0438&nbsp;</span><span class=\"hps\">\u043d\u0435 \u0443\u0434\u0438\u0432\u0438\u0442\u0435\u043b\u044c\u043d\u043e, \u0435\u0441\u043b\u0438&nbsp;</span><span class=\"hps\">\u0443\u0447\u0435\u0441\u0442\u044c \u0442\u043e\u0442 \u0444\u0430\u043a\u0442, \u0447\u0442\u043e \u0438\u0437\u0434\u0430\u0442\u0435\u043b\u044c\u0441\u0442\u0432\u043e Kosmos</span>&nbsp;<span class=\"hps\">\u044f\u0432\u043b\u044f\u0435\u0442\u0441\u044f</span>&nbsp;<span class=\"hps\">\u0435\u0432\u0440\u043e\u043f\u0435\u0439\u0441\u043a\u0438\u043c</span>.&nbsp;</span></div>\r\n</div>\r\n<div id=\"gt-res-tools\" style=\"text-align: justify;\">\r\n<div id=\"gt-res-tools-r\">\r\n<div id=\"gt-res-listen\" class=\"trans-listen-button goog-toolbar-button\"><span class=\"jfk-button-img\">&nbsp;</span></div>\r\n<div id=\"gt-res-roman\" class=\"trans-roman-button goog-toolbar-button\"><span class=\"jfk-button-img\">&nbsp;</span></div>\r\n<div id=\"gt-res-rate\">\r\n<div class=\"goog-inline-block goog-toolbar-menu-button\">\r\n<div class=\"goog-inline-block goog-toolbar-menu-button-outer-box\">\r\n<div class=\"goog-inline-block goog-toolbar-menu-button-inner-box\">\r\n<div class=\"goog-inline-block goog-toolbar-menu-button-caption\"><span class=\"goog-flat-menu-button-img gt-rate-icon jfk-button-img\">&nbsp;</span></div>\r\n</div>\r\n</div>\r\n</div>\r\n</div>\r\n</div>\r\n</div>\r\n</div>", "modificationDateUtc": "2019-03-08T07:28:18", "creationDateUtc": "2012-04-14T14:04:31", "photoUrl": "https://s.tesera.ru/images/items/115777,3/photo1.jpg", "photoUrl2": "https://s.tesera.ru/images/items/115777,3/photo2.jpg", "year": 2011, "ratingUser": 7.35, "n10Rating": 0.0, "n20Rating": 0.0, "bggRating": 6.649, "bggGeekRating": 5.769, "bggNumVotes": 626, "numVotes": 5, "playersMin": 3, "playersMax": 4, "playersMinRecommend": 3, "playersMaxRecommend": 4, "playersAgeMin": 12, "timeToLearn": 0, "playtimeMin": 0, "playtimeMax": 90, "commentsTotal": 1, "commentsTotalNew": 0, "teseraUrl": "https://tesera.ru/game/115777", "isAddition": false}, "ownersTotal": 8, "sellTotal": 0, "buyTotal": 0, "sellTotalAll": 1, "buyTotalAll": 0, "commentsTotal": 1, "reportsTotal": 0, "photosTotal": 4, "filesTotal": 5, "linksTotal": 2, "videoExternalTotal": 0, "videoInternalTotal": 0, "photos": [{"teseraId": 115785, "title": "\u0438\u0433\u0440\u043e\u0432\u043e\u0439 \u043f\u0440\u043e\u0446\u0435\u0441\u0441", "photoUrl": "https://s.tesera.ru/images/items/115785/1600x1200xsxy/photo.jpg", "creationDateUtc": "2012-04-14T14:12:16", "commentsTotal": 0, "author": {"teseraId": 34273, "id": 531, "login": "kosulya", "name": "Alexey Abramov", "avatarUrl": "https://s.tesera.ru/images/items/34273,22/photo.jpg", "rating": 12219, "teseraUrl": "https://tesera.ru/user/34273"}}, {"teseraId": 115784, "title": "\u043a\u043e\u043c\u043f\u043e\u043d\u0435\u043d\u0442\u044b \u043d\u0430 \u043f\u043e\u043b\u0435", "photoUrl": "https://s.tesera.ru/images/items/115784/1600x1200xsxy/photo.jpg", "creationDateUtc": "2012-04-14T14:11:50", "commentsTotal": 0, "author": {"teseraId": 34273, "id": 531, "login": "kosulya", "name": "Alexey Abramov", "avatarUrl": "https://s.tesera.ru/images/items/34273,22/photo.jpg", "rating": 12219, "teseraUrl": "https://tesera.ru/user/34273"}}, {"teseraId": 115783, "title": "\u0438\u0433\u0440\u043e\u0432\u044b\u0435 \u043a\u0430\u0440\u0442\u044b", "photoUrl": "https://s.tesera.ru/images/items/115783/1600x1200xsxy/photo.jpg", "creationDateUtc": "2012-04-14T14:11:10", "commentsTotal": 0, "author": {"teseraId": 34273, "id": 531, "login": "kosulya", "name": "Alexey Abramov", "avatarUrl": "https://s.tesera.ru/images/items/34273,22/photo.jpg", "rating": 12219, "teseraUrl": "https://tesera.ru/user/34273"}}, {"teseraId": 115781, "title": "\u0420\u0435\u0441\u0443\u0440\u0441\u044b", "photoUrl": "https://s.tesera.ru/images/items/115781/1600x1200xsxy/photo.jpg", "creationDateUtc": "2012-04-14T14:10:42", "commentsTotal": 0, "author": {"teseraId": 34273, "id": 531, "login": "kosulya", "name": "Alexey Abramov", "avatarUrl": "https://s.tesera.ru/images/items/34273,22/photo.jpg", "rating": 12219, "teseraUrl": "https://tesera.ru/user/34273"}}], "files": [{"teseraId": 411213, "objectType": "Game", "title": "\u041f\u0440\u0430\u0432\u0438\u043b\u0430 \u0438\u0433\u0440\u044b", "content": "\u0420\u0443\u0441\u0441\u043a\u0438\u0439 \u044f\u0437\u044b\u043a (HobbyWorld), pdf", "photoUrl": "https://tesera.ru/images/items/411213/kolon_europ_rules.pdf", "modificationDateUtc": "2014-05-28T16:45:33", "creationDateUtc": "2014-05-28T16:45:33", "author": {"teseraId": 34273, "id": 531, "login": "kosulya", "name": "Alexey Abramov", "avatarUrl": "https://s.tesera.ru/images/items/34273,22/photo.jpg", "rating": 12219, "teseraUrl": "https://tesera.ru/user/34273"}}, {"teseraId": 287823, "objectType": "Game", "title": "\u041f\u0440\u0430\u0432\u0438\u043b\u0430 \u0438\u0433\u0440\u044b", "content": "\u0420\u0443\u0441\u0441\u043a\u0438\u0439 \u044f\u0437\u044b\u043a, pdf", "photoUrl": "https://tesera.ru/images/items/287823/catan_moe_rules_rus.pdf", "modificationDateUtc": "2013-07-08T12:01:53", "creationDateUtc": "2013-07-08T12:01:53", "author": {"teseraId": 34273, "id": 531, "login": "kosulya", "name": "Alexey Abramov", "avatarUrl": "https://s.tesera.ru/images/items/34273,22/photo.jpg", "rating": 12219, "teseraUrl": "https://tesera.ru/user/34273"}}, {"teseraId": 287194, "objectType": "Game", "title": "\u041f\u0440\u0430\u0432\u0438\u043b\u0430 \u0438\u0433\u0440\u044b", "content": "\u0430\u043d\u0433\u043b\u0438\u0439\u0441\u043a\u0438\u0439 \u044f\u0437\u044b\u043a, pdf", "photoUrl": "https://tesera.ru/images/items/287194/catan_moe_rules_090612s.pdf", "modificationDateUtc": "2013-07-06T12:13:25", "creationDateUtc": "2013-07-06T12:13:24", "author": {"teseraId": 34273, "id": 531, "login": "kosulya", "name": "Alexey Abramov", "avatarUrl": "https://s.tesera.ru/images/items/34273,22/photo.jpg", "rating": 12219, "teseraUrl": "https://tesera.ru/user/34273"}}, {"teseraId": 115779, "objectType": "Game", "title": "\u041f\u0435\u0440\u0435\u0432\u043e\u0434 \u043f\u0440\u0430\u0432\u0438\u043b \u043d\u0430 \u0430\u043d\u0433\u043b\u0438\u0439\u0441\u043a\u0438\u0439 \u044f\u0437\u044b\u043a", "content": "\u0432 \u0444\u043e\u0440\u043c\u0430\u0442\u0435 .pdf", "photoUrl": "https://tesera.ru/images/items/115779/TRANSLATION_Settlers_of_Catan_Dawn_of_the_merchants.pdf", "modificationDateUtc": "2012-04-14T14:06:51", "creationDateUtc": "2012-04-14T14:06:51", "author": {"teseraId": 34273, "id": 531, "login": "kosulya", "name": "Alexey Abramov", "avatarUrl": "https://s.tesera.ru/images/items/34273,22/photo.jpg", "rating": 12219, "teseraUrl": "https://tesera.ru/user/34273"}}, {"teseraId": 115778, "objectType": "Game", "title": "\u041f\u0440\u0430\u0432\u0438\u043b\u0430 \u043d\u0430 \u043d\u0435\u043c\u0435\u0446\u043a\u043e\u043c \u044f\u0437\u044b\u043a\u0435", "content": "\u0432 \u0444\u043e\u0440\u043c\u0430\u0442\u0435 .pdf", "photoUrl": "https://tesera.ru/images/items/115778/Spielregel_DieSiedlervonCatan_AufbruchderH\u00e4ndler_694418.pdf", "modificationDateUtc": "2012-04-14T14:05:47", "creationDateUtc": "2012-04-14T14:05:46", "author": {"teseraId": 34273, "id": 531, "login": "kosulya", "name": "Alexey Abramov", "avatarUrl": "https://s.tesera.ru/images/items/34273,22/photo.jpg", "rating": 12219, "teseraUrl": "https://tesera.ru/user/34273"}}], "links": [{"teseraId": 425231, "objectType": "Game", "title": "\u041a\u043e\u043b\u043e\u043d\u0438\u0437\u0430\u0442\u043e\u0440\u044b. \u0415\u0432\u0440\u043e\u043f\u0430. \u0420\u0430\u0441\u0448\u0438\u0440\u044f\u0435\u043c \u0433\u0440\u0430\u043d\u0438\u0446\u044b \u041a\u0430\u0442\u0430\u043d\u0430", "photoUrl": "http://www.2fishki.ru/obzory_igr/kolonizatory_evropa_rasshiryaem_granitcy_katana/", "modificationDateUtc": "2014-07-21T22:09:54", "creationDateUtc": "2014-07-15T18:27:23", "author": {"teseraId": 16628, "id": 306, "login": "gravicapa", "name": "\u0410\u043b\u0435\u043a\u0441\u0430\u043d\u0434\u0440", "avatarUrl": "https://s.tesera.ru/images/items/16628,22/photo.jpg", "rating": 14858, "teseraUrl": "https://tesera.ru/user/16628"}}, {"teseraId": 115931, "objectType": "Game", "title": "\u041e\u0431\u0437\u043e\u0440 \u0438\u0433\u0440\u044b", "photoUrl": "http://tesera.ru/user/Lizaraduga/journal/115762/", "modificationDateUtc": "2012-04-15T12:25:08", "creationDateUtc": "2012-04-15T12:25:08", "author": {"teseraId": 25262, "id": 407, "login": "lizaraduga", "name": "\u041b\u0438\u0437\u0430 \u0412\u043e\u043b\u043a\u043e\u0432\u0430", "avatarUrl": "https://s.tesera.ru/images/items/25262,22/photo.jpg", "rating": 995, "teseraUrl": "https://tesera.ru/user/25262"}}], "similars": [], "relateds": [{"id": 4, "teseraId": 12, "bggId": 926, "title": "\u041a\u043e\u043b\u043e\u043d\u0438\u0437\u0430\u0442\u043e\u0440\u044b: \u0413\u043e\u0440\u043e\u0434\u0430 \u0438 \u0440\u044b\u0446\u0430\u0440\u0438. \u0427\u0435\u0442\u0432\u0451\u0440\u0442\u043e\u0435 \u0438\u0437\u0434\u0430\u043d\u0438\u0435", "title2": "Catan: Cities & Knights", "alias": "catan-cities-knights", "descriptionShort": "\u041d\u0430 \u0431\u043e\u0433\u0430\u0442\u044b\u0439 \u041a\u0430\u0442\u0430\u043d \u043d\u0430\u0434\u0432\u0438\u0433\u0430\u0435\u0442\u0441\u044f \u0432\u0430\u0440\u0432\u0430\u0440\u0441\u043a\u0438\u0439 \u0444\u043b\u043e\u0442. \u0427\u0442\u043e\u0431\u044b \u043f\u0440\u043e\u0442\u0438\u0432\u043e\u0441\u0442\u043e\u044f\u0442\u044c \u0432\u0430\u0440\u0432\u0430\u0440\u0430\u043c \u043a\u0430\u0436\u0434\u044b\u0439 \u0438\u0437 \u0438\u0433\u0440\u043e\u043a\u043e\u0432 \u0434\u043e\u043b\u0436\u0435\u043d \u0432\u044b\u0441\u0442\u0430\u0432\u0438\u0442\u044c \u0434\u043e\u0441\u0442\u0430\u0442\u043e\u0447\u043d\u043e\u0435 \u043a\u043e\u043b\u0438\u0447\u0435\u0441\u0442\u0432\u043e \u0441\u0432\u043e\u0438\u0445 \u0440\u044b\u0446\u0430\u0440\u0435\u0439...", "creationDateUtc": "2009-05-21T04:13:28", "photoUrl": "https://s.tesera.ru/images/items/12,3/200x200xpa/photo1.jpg", "year": 1998, "numVotes": 233, "ratingUser": 7.58, "n10Rating": 7.48, "n20Rating": 7.39, "bggRating": 7.451, "bggGeekRating": 7.172, "bggNumVotes": 19108, "commentsTotal": 43, "commentsTotalNew": 0, "isAddition": true}, {"id": 73, "teseraId": 1001, "bggId": 27760, "title": "\u041a\u043e\u043b\u043e\u043d\u0438\u0437\u0430\u0442\u043e\u0440\u044b. \u041a\u0443\u043f\u0446\u044b \u0438 \u0432\u0430\u0440\u0432\u0430\u0440\u044b", "title2": "Catan: Traders & Barbarians", "alias": "catan-traders-and-barbarians", "descriptionShort": "\u0414\u043b\u044f \u0438\u0433\u0440\u044b \u043d\u0435\u043e\u0431\u0445\u043e\u0434\u0438\u043c\u043e \u0438\u043c\u0435\u0442\u044c \u0431\u0430\u0437\u043e\u0432\u044b\u0439 \u043d\u0430\u0431\u043e\u0440 \u043d\u0430\u0441\u0442\u043e\u043b\u044c\u043d\u044b\u0445 \u041a\u043e\u043b\u043e\u043d\u0438\u0437\u0430\u0442\u043e\u0440\u043e\u0432. \u041a\u043e\u043b\u043e\u043d\u0438\u0437\u0430\u0442\u043e\u0440\u044b: \u041a\u0443\u043f\u0446\u044b \u0438 \u0412\u0430\u0440\u0432\u0430\u0440\u044b - \u044d\u0442\u043e \u043d\u0435\u0441\u043a\u043e\u043b\u044c\u043a\u043e \u0438\u0433\u0440 \u0432 \u043e\u0434\u043d\u043e\u0439 \u043a\u043e\u0440\u043e\u0431\u043a\u0435. \u0412\u0441\u0435 \u0442\u0435 \u0434\u0435\u0441\u044f\u0442\u044c...", "creationDateUtc": "2009-11-03T16:04:34", "photoUrl": "https://s.tesera.ru/images/items/1001,3/200x200xpa/photo1.png", "year": 2007, "numVotes": 99, "ratingUser": 7.16, "n10Rating": 6.98, "n20Rating": 6.83, "bggRating": 6.964, "bggGeekRating": 6.476, "bggNumVotes": 4739, "commentsTotal": 14, "commentsTotalNew": 0, "isAddition": true}, {"id": 74, "teseraId": 1002, "bggId": 13, "title": "\u041a\u043e\u043b\u043e\u043d\u0438\u0437\u0430\u0442\u043e\u0440\u044b", "title2": "The Settlers of Catan", "alias": "the-settlers-of-catan", "descriptionShort": "\u042d\u043f\u043e\u0445\u0430 \u0433\u0435\u043e\u0433\u0440\u0430\u0444\u0438\u0447\u0435\u0441\u043a\u0438\u0445 \u043e\u0442\u043a\u0440\u044b\u0442\u0438\u0439 \u0438 \u0434\u0435\u0440\u0437\u043a\u0438\u0445 \u0431\u0440\u043e\u0441\u043a\u043e\u0432 \u0432 \u043d\u0435\u0438\u0437\u0432\u0435\u0441\u0442\u043d\u043e\u0441\u0442\u044c \u0441\u043c\u0435\u043d\u044f\u0435\u0442\u0441\u044f \u0432\u0440\u0435\u043c\u0435\u043d\u0435\u043c \u043f\u043b\u0430\u043d\u043e\u043c\u0435\u0440\u043d\u043e\u0433\u043e \u043e\u0441\u0432\u043e\u0435\u043d\u0438\u044f. \u041e\u0441\u0442\u0440\u043e\u0432\u0430 \u0438 \u043c\u0430\u0442\u0435\u0440\u0438\u043a\u0438, \u043d\u0435\u0434\u0430\u0432\u043d\u0438\u0435 \u0431\u0435\u043b\u044b\u0435 \u043f\u044f\u0442\u043d\u0430...", "creationDateUtc": "2009-11-03T16:05:58", "photoUrl": "https://s.tesera.ru/images/items/1002,3/200x200xpa/photo1.jpg", "year": 1995, "numVotes": 1763, "ratingUser": 7.14, "n10Rating": 7.13, "n20Rating": 7.12, "bggRating": 7.109, "bggGeekRating": 6.939, "bggNumVotes": 118386, "commentsTotal": 421, "commentsTotalNew": 0, "isAddition": false}, {"id": 75, "teseraId": 1081, "bggId": 0, "title": "\u041a\u043e\u043b\u043e\u043d\u0438\u0437\u0430\u0442\u043e\u0440\u044b. \u041c\u043e\u0440\u0435\u0445\u043e\u0434\u044b", "title2": "Catan: Seafarers", "alias": "catan-seafarers", "descriptionShort": "\u041f\u043e\u0434\u043d\u0438\u043c\u0435\u043c\u0441\u044f \u0432\u044b\u0448\u0435 \u043d\u0430\u0434 \u043e\u0441\u0442\u0440\u043e\u0432\u043e\u043c \u041a\u0430\u0442\u0430\u043d, \u0438 \u043c\u044b \u0443\u0432\u0438\u0434\u0438\u043c \u0438\u0441\u0442\u0438\u043d\u043d\u044b\u0439 \u043c\u0430\u0441\u0448\u0442\u0430\u0431 \u0442\u043e\u0439 \u0442\u044f\u0433\u0438 \u043a \u043d\u0435\u0438\u0437\u0432\u0435\u0434\u0430\u043d\u043d\u043e\u043c\u0443, \u043a\u043e\u0442\u043e\u0440\u0430\u044f \u043f\u0440\u0438\u0432\u0435\u043b\u0430 \u043a\u043e\u043b\u043e\u043d\u0438\u0437\u0430\u0442\u043e\u0440\u043e\u0432 \u0432 \u044d\u0442\u043e\u0442 \u0443\u0433\u043e\u043b\u043e\u043a \u043c\u0438\u0440\u0430. \u0418 \u043a\u0430\u043a...", "creationDateUtc": "2009-11-06T13:11:27", "photoUrl": "https://s.tesera.ru/images/items/1081,3/200x200xpa/photo1.png", "year": 1997, "numVotes": 219, "ratingUser": 7.29, "n10Rating": 7.2, "n20Rating": 7.11, "bggRating": 7.13, "bggGeekRating": 0.0, "bggNumVotes": 0, "commentsTotal": 15, "commentsTotalNew": 0, "isAddition": true}, {"id": 1059, "teseraId": 7869, "bggId": 67239, "title": "\u041a\u043e\u043b\u043e\u043d\u0438\u0437\u0430\u0442\u043e\u0440\u044b. \u0410\u043c\u0435\u0440\u0438\u043a\u0430", "title2": "Settlers of America: Trails to Rails", "title3": "Catan Histories: Settlers of America, Catan Histories: Settlers of America Trails to Rails, De Kolonisten van Amerika", "alias": "settlers-of-america-trails-to-rails", "descriptionShort": "\u0412 1869 \u0433\u043e\u0434\u0443 \u0432 \u0421\u0428\u0410 \u0431\u044b\u043b\u0430 \u043e\u0442\u043a\u0440\u044b\u0442\u0430 \u043f\u0435\u0440\u0432\u0430\u044f \u0442\u0440\u0430\u043d\u0441\u043a\u043e\u043d\u0442\u0438\u043d\u0435\u043d\u0442\u0430\u043b\u044c\u043d\u0430\u044f \u0436\u0435\u043b\u0435\u0437\u043d\u0430\u044f \u0434\u043e\u0440\u043e\u0433\u0430, \u0430 \u043a \u043a\u043e\u043d\u0446\u0443 \u0434\u0435\u0432\u044f\u0442\u043d\u0430\u0434\u0446\u0430\u0442\u043e\u0433\u043e \u0432\u0435\u043a\u0430 \u0438\u0445 \u0441\u0442\u0430\u043b\u043e \u0443\u0436\u0435 \u043f\u044f\u0442\u044c. \u0418\u043c\u0435\u043d\u043d\u043e \u0432 \u044d\u0442\u0443...", "creationDateUtc": "2010-08-21T07:43:41", "photoUrl": "https://s.tesera.ru/images/items/7869,3/200x200xpa/photo1.jpg", "year": 2010, "numVotes": 36, "ratingUser": 7.23, "n10Rating": 6.78, "n20Rating": 6.49, "bggRating": 6.797, "bggGeekRating": 6.201, "bggNumVotes": 2414, "commentsTotal": 7, "commentsTotalNew": 0, "isAddition": false}, {"id": 6342, "teseraId": 320780, "bggId": 103091, "title": "\u041a\u043e\u043b\u043e\u043d\u0438\u0437\u0430\u0442\u043e\u0440\u044b. \u0415\u0432\u0440\u043e\u043f\u0430", "title2": "Catan Histories: Merchants of Europe", "alias": "Catan-Histories-Merchants-of-Europe", "descriptionShort": "\u0421\u043e\u0431\u044b\u0442\u0438\u044f \u0438\u0433\u0440\u044b \u00ab\u041a\u043e\u043b\u043e\u043d\u0438\u0437\u0430\u0442\u043e\u0440\u044b. \u0415\u0432\u0440\u043e\u043f\u0430\u00bb \u043f\u0440\u043e\u0438\u0441\u0445\u043e\u0434\u044f\u0442 \u043d\u0430 \u0444\u0438\u043a\u0441\u0438\u0440\u043e\u0432\u0430\u043d\u043d\u043e\u043c \u0438\u0433\u0440\u043e\u0432\u043e\u043c \u043f\u043e\u043b\u0435, \u043f\u0440\u0435\u0434\u0441\u0442\u0430\u0432\u043b\u044f\u044e\u0449\u0435\u043c \u0441\u043e\u0431\u043e\u0439 \u043a\u0430\u0440\u0442\u0443 \u0415\u0432\u0440\u043e\u043f\u044b. \u041d\u0430 \u043d\u0430\u0447\u0430\u043b\u043e \u0438\u0433\u0440\u044b \u043a\u0430\u0436\u0434\u044b\u0439 \u0438\u0433\u0440\u043e\u043a,...", "creationDateUtc": "2013-10-03T15:26:11", "photoUrl": "https://s.tesera.ru/images/items/320780,3/200x200xpa/photo1.png", "year": 2011, "numVotes": 39, "ratingUser": 6.53, "n10Rating": 6.25, "n20Rating": 6.07, "bggRating": 6.649, "bggGeekRating": 5.769, "bggNumVotes": 626, "commentsTotal": 9, "commentsTotalNew": 0, "isAddition": false}, {"id": 31384, "teseraId": 1312871, "bggId": 13, "title": "catan trade build settle", "title3": "catan trade build settle MADE IN USA", "alias": "catan-trade-build-settle", "descriptionShort": "", "creationDateUtc": "2018-09-16T09:31:14", "photoUrl": "https://s.tesera.ru/images/items/1312871,3/200x200xpa/photo1.png", "year": 2016, "numVotes": 3, "ratingUser": 6.25, "n10Rating": 0.0, "n20Rating": 0.0, "bggRating": 7.109, "bggGeekRating": 6.939, "bggNumVotes": 118386, "commentsTotal": 0, "commentsTotalNew": 0, "isAddition": false}], "news": []}