{"game": {"id": 13599, "teseraId": 996480, "bggId": 0, "title": "Star Wars: Imperial Assault - Heart of the Empire", "alias": "star-wars-imperial-assault-heart-of-the-empire", "descriptionShort": "\u0414\u043e\u043f\u043e\u043b\u043d\u0435\u043d\u0438\u0435 \u043a Imperial Assault, \u0433\u0434\u0435 \u0433\u0435\u0440\u043e\u044f\u043c \u043f\u0440\u0435\u0434\u0441\u0442\u043e\u0438\u0442 \u043f\u043e\u0441\u0435\u0442\u0438\u0442\u044c \u0441\u0442\u043e\u043b\u0438\u0446\u0443 \u0418\u043c\u043f\u0435\u0440\u0438\u0438 - \u041a\u043e\u0440\u0443\u0441\u043a\u0430\u043d\u0442.", "description": "<p>\u0414\u043e\u043f\u043e\u043b\u043d\u0435\u043d\u0438\u0435 \u043a Imperial Assault, \u0433\u0434\u0435 \u0433\u0435\u0440\u043e\u044f\u043c \u043f\u0440\u0435\u0434\u0441\u0442\u043e\u0438\u0442 \u043f\u043e\u0441\u0435\u0442\u0438\u0442\u044c \u0441\u0442\u043e\u043b\u0438\u0446\u0443 \u0418\u043c\u043f\u0435\u0440\u0438\u0438 - \u041a\u043e\u0440\u0443\u0441\u043a\u0430\u043d\u0442.</p>\r\n<p>\u041f\u043e\u043c\u0438\u043c\u043e \u0442\u0440\u0435\u0445 \u043d\u043e\u0432\u044b\u0445 \u0433\u0435\u0440\u043e\u0435\u0432, \u0447\u0435\u0442\u044b\u0440\u0435\u0445 \u0432\u0438\u0434\u043e\u0432 \u043f\u0440\u043e\u0442\u0438\u0432\u043d\u0438\u043a\u043e\u0432 \u0438 \u0441\u0446\u0435\u043d\u0430\u0440\u0438\u0435\u0432 \u0434\u043e\u043f\u043e\u043b\u043d\u0435\u043d\u0438\u0435 \u0434\u0430\u0435\u0442 \u0438\u0433\u0440\u0435 \u043d\u043e\u0432\u044b\u0439 \u0442\u0438\u043f \u0436\u0435\u0442\u043e\u043d\u043e\u0432, \u043a\u043e\u0442\u043e\u0440\u044b\u0439 \u043c\u043e\u0436\u043d\u043e \u0441\u043a\u0438\u0434\u044b\u0432\u0430\u0442\u044c \u0447\u0442\u043e\u0431\u044b \u043f\u043e\u043b\u0443\u0447\u0430\u0442\u044c \u0432\u043e \u0432\u0440\u0435\u043c\u044f \u0431\u0440\u043e\u0441\u043a\u0430 \u043e\u043f\u0440\u0435\u0434\u0435\u043b\u0435\u043d\u043d\u044b\u0435 \u0437\u043d\u0430\u0447\u0435\u043d\u0438\u044f \u043a\u0443\u0431\u043e\u0432.</p>", "modificationDateUtc": "2019-08-15T23:10:24", "creationDateUtc": "2017-05-06T07:57:32", "photoUrl": "https://s.tesera.ru/images/items/996480,3/photo1.png", "year": 2017, "ratingUser": 0.0, "n10Rating": 0.0, "n20Rating": 0.0, "bggRating": 0.0, "bggGeekRating": 0.0, "bggNumVotes": 0, "numVotes": 0, "playersMin": 0, "playersMax": 0, "playersMinRecommend": 0, "playersMaxRecommend": 0, "playersAgeMin": 0, "timeToLearn": 0, "playtimeMin": 0, "playtimeMax": 0, "commentsTotal": 49, "commentsTotalNew": 0, "teseraUrl": "https://tesera.ru/game/996480", "isAddition": true}, "ownersTotal": 53, "sellTotal": 0, "buyTotal": 0, "sellTotalAll": 3, "buyTotalAll": 3, "commentsTotal": 49, "reportsTotal": 0, "photosTotal": 5, "filesTotal": 2, "linksTotal": 4, "videoExternalTotal": 1, "videoInternalTotal": 0, "photos": [{"teseraId": 996750, "title": "\u0424\u0438\u0433\u0443\u0440\u043a\u0438", "photoUrl": "https://s.tesera.ru/images/items/996750/1600x1200xsxy/photo.jpg", "creationDateUtc": "2017-05-06T20:49:40", "commentsTotal": 0, "author": {"teseraId": 367910, "id": 8157, "login": "reezo", "name": "ReeZo", "avatarUrl": "https://s.tesera.ru/images/items/367910,22/photo.jpg", "rating": 875, "teseraUrl": "https://tesera.ru/user/367910"}}, {"teseraId": 996748, "title": "\u041a\u0430\u0440\u0442\u043e\u0447\u043a\u0438", "photoUrl": "https://s.tesera.ru/images/items/996748/1600x1200xsxy/photo.jpg", "creationDateUtc": "2017-05-06T20:49:02", "commentsTotal": 1, "author": {"teseraId": 367910, "id": 8157, "login": "reezo", "name": "ReeZo", "avatarUrl": "https://s.tesera.ru/images/items/367910,22/photo.jpg", "rating": 875, "teseraUrl": "https://tesera.ru/user/367910"}}, {"teseraId": 996746, "title": "\u0413\u0435\u0440\u043e\u0438", "photoUrl": "https://s.tesera.ru/images/items/996746/1600x1200xsxy/photo.jpg", "creationDateUtc": "2017-05-06T20:48:01", "commentsTotal": 0, "author": {"teseraId": 367910, "id": 8157, "login": "reezo", "name": "ReeZo", "avatarUrl": "https://s.tesera.ru/images/items/367910,22/photo.jpg", "rating": 875, "teseraUrl": "https://tesera.ru/user/367910"}}, {"teseraId": 996483, "title": "\u041a\u0430\u0440\u0442\u043e\u0447\u043a\u0430 \u0433\u0435\u0440\u043e\u044f.", "photoUrl": "https://s.tesera.ru/images/items/996483/1600x1200xsxy/photo.jpg", "creationDateUtc": "2017-05-06T08:01:52", "commentsTotal": 0, "author": {"teseraId": 263569, "id": 5810, "login": "desert_witch", "name": "Desert_witch", "avatarUrl": "https://s.tesera.ru/images/items/263569,22/photo.jpg", "rating": 66242, "teseraUrl": "https://tesera.ru/user/263569"}}, {"teseraId": 996482, "title": "\u0421\u043e\u0434\u0435\u0440\u0436\u0438\u043c\u043e\u0435 \u043a\u043e\u0440\u043e\u0431\u043a\u0438.", "photoUrl": "https://s.tesera.ru/images/items/996482/1600x1200xsxy/photo.png", "creationDateUtc": "2017-05-06T08:00:42", "commentsTotal": 0, "author": {"teseraId": 263569, "id": 5810, "login": "desert_witch", "name": "Desert_witch", "avatarUrl": "https://s.tesera.ru/images/items/263569,22/photo.jpg", "rating": 66242, "teseraUrl": "https://tesera.ru/user/263569"}}], "files": [{"teseraId": 1394457, "objectType": "Game", "title": "\u0416\u0443\u0440\u043d\u0430\u043b \u043a\u0430\u043c\u043f\u0430\u043d\u0438\u0438 [eng]", "content": "\u0422\u043e\u043b\u044c\u043a\u043e \u043f\u0440\u0430\u0432\u0438\u043b\u0430, \u0431\u0435\u0437 \u043c\u0438\u0441\u0441\u0438\u0439 \u043a\u043e\u043c\u043f\u0430\u043d\u0438\u0438!", "photoUrl": "https://tesera.ru/images/items/1394457/swi46_rulebook_nomissions.pdf", "modificationDateUtc": "2019-01-27T22:59:42", "creationDateUtc": "2019-01-27T22:59:42", "author": {"teseraId": 1153874, "id": 26874, "login": "totace", "name": "ToTaCe", "avatarUrl": "https://s.tesera.ru/images/items/1153874,22/photo.png", "rating": 1421, "teseraUrl": "https://tesera.ru/user/1153874"}}, {"teseraId": 1394450, "objectType": "Game", "title": "\u0416\u0443\u0440\u043d\u0430\u043b \u043a\u0430\u043c\u043f\u0430\u043d\u0438\u0438 [eng]", "photoUrl": "https://tesera.ru/images/items/1394450/IA Heart of the Empire Campaign Log.pdf", "modificationDateUtc": "2019-01-27T22:45:03", "creationDateUtc": "2019-01-27T22:45:02", "author": {"teseraId": 1153874, "id": 26874, "login": "totace", "name": "ToTaCe", "avatarUrl": "https://s.tesera.ru/images/items/1153874,22/photo.png", "rating": 1421, "teseraUrl": "https://tesera.ru/user/1153874"}}], "links": [{"teseraId": 1507929, "objectType": "Game", "title": "Heart of the Empire \u041a\u043d\u0438\u0433\u0430 \u0437\u0430\u0434\u0430\u043d\u0438\u0439", "photoUrl": "http://www.mediafire.com/file/fhk0qqyzvot5w04/Addon_5_Heart_of_the_Empire_%2528RUS%2529.rar/file", "modificationDateUtc": "2019-08-15T23:09:33", "creationDateUtc": "2019-08-15T23:09:32", "author": {"teseraId": 1153874, "id": 26874, "login": "totace", "name": "ToTaCe", "avatarUrl": "https://s.tesera.ru/images/items/1153874,22/photo.png", "rating": 1421, "teseraUrl": "https://tesera.ru/user/1153874"}}, {"teseraId": 1486368, "objectType": "Game", "title": "Heart of the Empire rulebook [eng]", "photoUrl": "http://www.mediafire.com/file/a76kfbayk8wv94f/Heart_of_the_Empire_rulebook_FULL.pdf/file", "modificationDateUtc": "2019-07-11T18:08:33", "creationDateUtc": "2019-07-11T18:08:32", "author": {"teseraId": 1153874, "id": 26874, "login": "totace", "name": "ToTaCe", "avatarUrl": "https://s.tesera.ru/images/items/1153874,22/photo.png", "rating": 1421, "teseraUrl": "https://tesera.ru/user/1153874"}}, {"teseraId": 1361976, "objectType": "Game", "title": "\u0421\u0442\u0440\u0430\u043d\u0438\u0446\u0430 \u0434\u043e\u043f\u043e\u043b\u043d\u0435\u043d\u0438\u044f \u043d\u0430 \u0432\u0438\u043a\u0438 [eng]", "photoUrl": "http://imperial-assault.wikia.com/wiki/Heart_of_the_Empire", "modificationDateUtc": "2018-12-14T14:22:26", "creationDateUtc": "2018-12-14T14:22:26", "author": {"teseraId": 1153874, "id": 26874, "login": "totace", "name": "ToTaCe", "avatarUrl": "https://s.tesera.ru/images/items/1153874,22/photo.png", "rating": 1421, "teseraUrl": "https://tesera.ru/user/1153874"}}, {"teseraId": 996485, "objectType": "Game", "title": "\u0410\u043d\u043e\u043d\u0441 \u043d\u0430 \u0441\u0430\u0439\u0442\u0435 FFG.", "photoUrl": "https://www.fantasyflightgames.com/en/news/2017/5/5/heart-of-the-empire/", "modificationDateUtc": "2017-11-29T02:07:48", "creationDateUtc": "2017-05-06T08:04:29", "author": {"teseraId": 263569, "id": 5810, "login": "desert_witch", "name": "Desert_witch", "avatarUrl": "https://s.tesera.ru/images/items/263569,22/photo.jpg", "rating": 66242, "teseraUrl": "https://tesera.ru/user/263569"}}], "similars": [], "relateds": [{"id": 13633, "teseraId": 998212, "bggId": 0, "title": "Star Wars: Imperial Assault \u2014 Maul Villain Pack", "alias": "star-wars-imperial-assault-maul-villain-pack", "descriptionShort": "", "creationDateUtc": "2017-05-10T07:20:24", "photoUrl": "https://s.tesera.ru/images/items/998212,3/200x200xpa/photo1.jpg", "year": 2017, "numVotes": 0, "ratingUser": 0.0, "n10Rating": 0.0, "n20Rating": 0.0, "bggRating": 0.0, "bggGeekRating": 0.0, "bggNumVotes": 0, "commentsTotal": 0, "commentsTotalNew": 0, "isAddition": true}, {"id": 13639, "teseraId": 998227, "bggId": 0, "title": "Star Wars: Imperial Assault \u2014 Emperor Palpatine Villain Pack", "alias": "star-wars-imperial-assault-emperor-palpatine-villain-pack", "descriptionShort": "", "creationDateUtc": "2017-05-10T07:31:24", "photoUrl": "https://s.tesera.ru/images/items/998227,3/200x200xpa/photo1.jpg", "year": 2017, "numVotes": 0, "ratingUser": 0.0, "n10Rating": 0.0, "n20Rating": 0.0, "bggRating": 0.0, "bggGeekRating": 0.0, "bggNumVotes": 0, "commentsTotal": 2, "commentsTotalNew": 0, "isAddition": true}, {"id": 13636, "teseraId": 998233, "bggId": 0, "title": "Star Wars: Imperial Assault \u2014 Ahsoka Tano Ally Pack", "alias": "star-wars-imperial-assault-ahsoka-tano-ally-pack", "descriptionShort": "", "creationDateUtc": "2017-05-10T07:37:42", "photoUrl": "https://s.tesera.ru/images/items/998233,3/200x200xpa/photo1.jpg", "year": 0, "numVotes": 0, "ratingUser": 0.0, "n10Rating": 0.0, "n20Rating": 0.0, "bggRating": 0.0, "bggGeekRating": 0.0, "bggNumVotes": 0, "commentsTotal": 0, "commentsTotalNew": 0, "isAddition": true}], "news": [{"teseraId": 998194, "title": "\u0412\u043e\u0437\u043c\u0443\u0449\u0435\u043d\u0438\u044f \u0432 \u0441\u0438\u043b\u0435", "alias": "998194", "contentShort": "\u041a Star Wars: Imperial Assault \u0430\u043d\u043e\u043d\u0441\u0438\u0440\u043e\u0432\u0430\u043d\u044b 3 \u043d\u043e\u0432\u044b\u0445 \u043d\u0430\u0431\u043e\u0440\u0430 \u0441\u043e\u044e\u0437\u043d\u0438\u043a\u043e\u0432/\u0437\u043b\u043e\u0434\u0435\u0435\u0432.", "creationDateUtc": "2017-05-10T06:56:17", "modificationDateUtc": "2020-08-23T17:32:07", "publicationDateUtc": "2017-05-10T09:57:00", "photoUrl": "https://s.tesera.ru/images/items/998194,18/125x125xpa/photo.png", "rating": 7.81, "commentsTotal": 24, "numVotes": 42}, {"teseraId": 998250, "title": "Star Wars: Imperial Assault \u2014 \u00abC\u0435\u0440\u0434\u0446\u0435 \u0418\u043c\u043f\u0435\u0440\u0438\u0438\u00bb", "alias": "998250", "contentShort": "\u0410\u043d\u043e\u043d\u0441\u0438\u0440\u043e\u0432\u0430\u043d\u043e \u0434\u043e\u043f\u043e\u043b\u043d\u0435\u043d\u0438\u0435 Heart of the Empire \u0434\u043b\u044f Star Wars: Imperial Assault.", "creationDateUtc": "2017-05-10T07:55:16", "modificationDateUtc": "2020-08-23T17:32:12", "publicationDateUtc": "2017-05-10T10:04:00", "photoUrl": "https://s.tesera.ru/images/items/998250,18/125x125xpa/photo.png", "rating": 8.17, "commentsTotal": 14, "numVotes": 47}]}