{"game": {"id": 5493, "teseraId": 238128, "bggId": 133654, "title": "Star Wars LCG: The Desolation of Hoth", "alias": "star-wars-lcg-the-desolation-of-hoth", "descriptionShort": "\u041f\u0435\u0440\u0432\u043e\u0435 \u0434\u043e\u043f\u043e\u043b\u043d\u0435\u043d\u0438\u0435 \"\u0425\u043e\u0442\u0441\u043a\u043e\u0433\u043e \u0446\u0438\u043a\u043b\u0430\".", "description": "<p>\u041f\u0435\u0440\u0432\u043e\u0435 \u0434\u043e\u043f\u043e\u043b\u043d\u0435\u043d\u0438\u0435 \"\u0425\u043e\u0442\u0441\u043a\u043e\u0433\u043e \u0446\u0438\u043a\u043b\u0430\".</p>", "modificationDateUtc": "2019-08-13T11:42:33", "creationDateUtc": "2013-03-21T14:25:15", "photoUrl": "https://s.tesera.ru/images/items/238128,3/photo1.jpg", "year": 2012, "ratingUser": 8.0, "n10Rating": 0.0, "n20Rating": 0.0, "bggRating": 7.515, "bggGeekRating": 5.769, "bggNumVotes": 331, "numVotes": 1, "playersMin": 2, "playersMax": 0, "playersMinRecommend": 2, "playersMaxRecommend": 0, "playersAgeMin": 10, "timeToLearn": 30, "playtimeMin": 30, "playtimeMax": 90, "commentsTotal": 0, "commentsTotalNew": 0, "teseraUrl": "https://tesera.ru/game/238128", "isAddition": true}, "ownersTotal": 9, "sellTotal": 0, "buyTotal": 0, "sellTotalAll": 0, "buyTotalAll": 1, "commentsTotal": 0, "reportsTotal": 0, "photosTotal": 17, "filesTotal": 0, "linksTotal": 2, "videoExternalTotal": 0, "videoInternalTotal": 0, "photos": [{"teseraId": 247285, "title": "wilderness-fighters", "photoUrl": "https://s.tesera.ru/images/items/247285/1600x1200xsxy/photo.png", "creationDateUtc": "2013-04-02T12:52:52", "commentsTotal": 0, "author": {"teseraId": 100421, "id": 2157, "login": "slai", "name": "\u0410\u043d\u0442\u043e\u043d", "avatarUrl": "https://s.tesera.ru/images/items/100421,22/photo.jpg", "rating": 4310, "teseraUrl": "https://tesera.ru/user/100421"}}, {"teseraId": 247284, "title": "the-killing-cold", "photoUrl": "https://s.tesera.ru/images/items/247284/1600x1200xsxy/photo.png", "creationDateUtc": "2013-04-02T12:51:56", "commentsTotal": 0, "author": {"teseraId": 100421, "id": 2157, "login": "slai", "name": "\u0410\u043d\u0442\u043e\u043d", "avatarUrl": "https://s.tesera.ru/images/items/100421,22/photo.jpg", "rating": 4310, "teseraUrl": "https://tesera.ru/user/100421"}}, {"teseraId": 247282, "title": "SWC06-cardfan-01", "photoUrl": "https://s.tesera.ru/images/items/247282/1600x1200xsxy/photo.png", "creationDateUtc": "2013-04-02T12:51:10", "commentsTotal": 0, "author": {"teseraId": 100421, "id": 2157, "login": "slai", "name": "\u0410\u043d\u0442\u043e\u043d", "avatarUrl": "https://s.tesera.ru/images/items/100421,22/photo.jpg", "rating": 4310, "teseraUrl": "https://tesera.ru/user/100421"}}, {"teseraId": 247280, "title": "subzero-defenses", "photoUrl": "https://s.tesera.ru/images/items/247280/1600x1200xsxy/photo.png", "creationDateUtc": "2013-04-02T12:50:48", "commentsTotal": 0, "author": {"teseraId": 100421, "id": 2157, "login": "slai", "name": "\u0410\u043d\u0442\u043e\u043d", "avatarUrl": "https://s.tesera.ru/images/items/100421,22/photo.jpg", "rating": 4310, "teseraUrl": "https://tesera.ru/user/100421"}}, {"teseraId": 247275, "title": "snowspeeder", "photoUrl": "https://s.tesera.ru/images/items/247275/1600x1200xsxy/photo.png", "creationDateUtc": "2013-04-02T12:50:23", "commentsTotal": 0, "author": {"teseraId": 100421, "id": 2157, "login": "slai", "name": "\u0410\u043d\u0442\u043e\u043d", "avatarUrl": "https://s.tesera.ru/images/items/100421,22/photo.jpg", "rating": 4310, "teseraUrl": "https://tesera.ru/user/100421"}}], "files": [], "links": [{"teseraId": 248812, "objectType": "Game", "title": "\u041a\u043e\u043d\u0442\u0435\u043d\u0442-\u043b\u0438\u0441\u0442 (\u043a\u043e\u043b\u0438\u0447\u0435\u0441\u0442\u0432\u043e \u043a\u0430\u0440\u0442) \u043f\u0435\u0440\u0432\u043e\u0433\u043e \u043f\u0430\u043a\u0430", "photoUrl": "http://kec-lcg.blogspot.ru/2013/03/the-desolation-of-hoth-contents-star.html", "modificationDateUtc": "2013-04-04T21:16:06", "creationDateUtc": "2013-04-04T21:16:05", "author": {"teseraId": 100421, "id": 2157, "login": "slai", "name": "\u0410\u043d\u0442\u043e\u043d", "avatarUrl": "https://s.tesera.ru/images/items/100421,22/photo.jpg", "rating": 4310, "teseraUrl": "https://tesera.ru/user/100421"}}, {"teseraId": 238709, "objectType": "Game", "title": "\u0421\u043f\u043e\u0439\u043b\u0435\u0440 \u043a\u0430\u0440\u0442 \u043f\u0435\u0440\u0432\u043e\u0433\u043e \u043f\u0430\u043a\u0430", "photoUrl": "http://kec-lcg.blogspot.ru/2013/03/the-desolation-of-hoth-spoilers-star.html", "modificationDateUtc": "2013-03-22T09:54:14", "creationDateUtc": "2013-03-22T09:54:14", "author": {"teseraId": 100421, "id": 2157, "login": "slai", "name": "\u0410\u043d\u0442\u043e\u043d", "avatarUrl": "https://s.tesera.ru/images/items/100421,22/photo.jpg", "rating": 4310, "teseraUrl": "https://tesera.ru/user/100421"}}], "similars": [], "relateds": [{"id": 5200, "teseraId": 210838, "bggId": 0, "title": "Star Wars: Edge of the Empire Beginner game", "alias": "star-wars-edge-of-the-empire-beginner-game", "descriptionShort": "", "creationDateUtc": "2013-01-20T18:10:17", "photoUrl": "https://s.tesera.ru/images/items/210838,3/200x200xpa/photo1.jpg", "year": 2012, "numVotes": 17, "ratingUser": 7.96, "n10Rating": 6.93, "n20Rating": 0.0, "bggRating": 0.0, "bggGeekRating": 0.0, "bggNumVotes": 0, "commentsTotal": 58, "commentsTotalNew": 0, "isAddition": true}, {"id": 5303, "teseraId": 220378, "bggId": 138170, "title": "Star Wars: The Card Game - Edge of Darkness", "title2": "Star Wars. \u041d\u0430 \u0433\u0440\u0430\u043d\u0438 \u0442\u044c\u043c\u044b", "alias": "Star-Wars-The-Card-Game-Edge-of-Darkness", "descriptionShort": "\u0412 \u043a\u043e\u0440\u043e\u0431\u043a\u0435 \u043f\u043e\u0434 \u043d\u0430\u0437\u0432\u0430\u043d\u0438\u0435\u043c \"Edge of Darkness\" \u0441\u043a\u0440\u044b\u0432\u0430\u044e\u0442\u0441\u044f 132 \u043a\u0430\u0440\u0442\u044b: 11 \u043d\u0430\u0431\u043e\u0440\u043e\u0432 \u0446\u0435\u043b\u0435\u0439 \u0434\u043b\u044f \u0441\u0432\u0435\u0442\u043b\u043e\u0439 \u0441\u0442\u043e\u0440\u043e\u043d\u044b \u0438 11 \u043d\u0430\u0431\u043e\u0440\u043e\u0432 \u0434\u043b\u044f \u0442\u0451\u043c\u043d\u043e\u0439. \u041f\u043e\u043c\u0438\u043c\u043e \u0441\u043e\u0431\u044b\u0442\u0438\u0439...", "creationDateUtc": "2013-02-12T12:56:04", "photoUrl": "https://s.tesera.ru/images/items/220378,3/200x200xpa/photo1.png", "year": 2013, "numVotes": 24, "ratingUser": 7.35, "n10Rating": 6.71, "n20Rating": 6.36, "bggRating": 7.662, "bggGeekRating": 5.928, "bggNumVotes": 520, "commentsTotal": 5, "commentsTotalNew": 0, "isAddition": true}, {"id": 5494, "teseraId": 238135, "bggId": 135222, "title": "Star Wars LCG: The Search for Skywalker", "alias": "star-wars-lcg-the-search-for-skywalker", "descriptionShort": "\u0412\u0442\u043e\u0440\u043e\u0435 \u0434\u043e\u043f\u043e\u043b\u043d\u0435\u043d\u0438\u0435 \"\u0425\u043e\u0442\u0441\u043a\u043e\u0433\u043e \u0446\u0438\u043a\u043b\u0430\".", "creationDateUtc": "2013-03-21T14:34:13", "photoUrl": "https://s.tesera.ru/images/items/238135,3/200x200xpa/photo1.jpg", "year": 2012, "numVotes": 1, "ratingUser": 8.0, "n10Rating": 0.0, "n20Rating": 0.0, "bggRating": 7.617, "bggGeekRating": 5.771, "bggNumVotes": 308, "commentsTotal": 0, "commentsTotalNew": 0, "isAddition": true}, {"id": 5495, "teseraId": 238142, "bggId": 0, "title": "Star Wars LCG: A Dark Time", "alias": "star-wars-lcg-a-dark-time", "descriptionShort": "\u0422\u0440\u0435\u0442\u044c\u0435 \u0434\u043e\u043f\u043e\u043b\u043d\u0435\u043d\u0438\u0435 \"\u0425\u043e\u0442\u0441\u043a\u043e\u0433\u043e \u0446\u0438\u043a\u043b\u0430\".", "creationDateUtc": "2013-03-21T14:40:38", "photoUrl": "https://s.tesera.ru/images/items/238142,3/200x200xpa/photo1.jpg", "year": 2012, "numVotes": 2, "ratingUser": 7.88, "n10Rating": 0.0, "n20Rating": 0.0, "bggRating": 0.0, "bggGeekRating": 0.0, "bggNumVotes": 0, "commentsTotal": 0, "commentsTotalNew": 0, "isAddition": true}, {"id": 5496, "teseraId": 238146, "bggId": 0, "title": "Star Wars LCG: Assault on Echo Base", "alias": "star-wars-lcg-assault-on-echo-base", "descriptionShort": "\u0427\u0435\u0442\u0432\u0435\u0440\u0442\u043e\u0435 \u0434\u043e\u043f\u043e\u043b\u043d\u0435\u043d\u0438\u0435 \"\u0425\u043e\u0442\u0441\u043a\u043e\u0433\u043e \u0446\u0438\u043a\u043b\u0430\".", "creationDateUtc": "2013-03-21T14:46:27", "photoUrl": "https://s.tesera.ru/images/items/238146,3/200x200xpa/photo1.jpg", "year": 2012, "numVotes": 1, "ratingUser": 8.0, "n10Rating": 0.0, "n20Rating": 0.0, "bggRating": 0.0, "bggGeekRating": 0.0, "bggNumVotes": 0, "commentsTotal": 0, "commentsTotalNew": 0, "isAddition": true}], "news": []}